{
  "auth": "zef:raku-community-modules",
  "authors": [
    "eater"
  ],
  "build-depends": [
  ],
  "depends": [
  ],
  "description": "Some simple but useful URL utils",
  "license": "Artistic-2.0",
  "name": "PostCocoon::Url",
  "perl": "6",
  "provides": {
    "PostCocoon::Url": "lib/PostCocoon/Url.rakumod"
  },
  "resources": [
  ],
  "source-url": "https://github.com/raku-community-modules/PostCocoon-Url.git",
  "tags": [
    "query string",
    "url",
    "http"
  ],
  "test-depends": [
  ],
  "version": "1.1"
}
